LICENSE
coverage.py
ez_setup.py
runtests.py
setup.py
unittests.cfg
utiltests.py
scripts/xix-coverage.py
tests/__init__.py
tests/data/fileaggr/file0.txt
tests/data/fileaggr/file1.txt
tests/data/fileaggr/file2.txt
tests/data/fileaggr/file3.txt
tests/data/fileaggr/file4.txt
tests/data/fileaggr/file5.txt
tests/data/fileaggr/file6.txt
tests/doctests/__init__.py
tests/doctests/upgrade_example.py
tests/doctests/txt/xix-utils-config-Sections.txt
tests/doctests/txt/xix-utils-config-SpanningLines.txt
tests/doctests/txt/xix-utils-cover-AnnotationParser.txt
tests/doctests/txt/xix-utils-cover-CoverageReportParser.txt
tests/doctests/txt/xix-utils-cover-annotationToXML.txt
tests/doctests/txt/xix-utils-cover-reportToXML.txt
tests/doctests/txt/xix-utils-diff-PrettyDiff-sort_cmpfunc.txt
tests/doctests/txt/xix-utils-io-AggregateFile-read.txt
tests/doctests/txt/xix-utils-io-AggregateFile-readline.txt
tests/doctests/txt/xix-utils-io-AggregateFile-readlines.txt
tests/doctests/txt/xix-utils-io-AggregateFile-seek0.txt
tests/doctests/txt/xix-utils-io-AggregateFile-seek1.txt
tests/doctests/txt/xix-utils-io-AggregateFile-seek2.txt
tests/doctests/txt/xix-utils-io-AggregateFileInput-iter.txt
tests/doctests/txt/xix-utils-python-Curried.txt
tests/doctests/txt/xix-utils-timetool-incrementMonth-end.txt
tests/doctests/txt/xix-utils-timetool-incrementMonth-middle.txt
tests/doctests/txt/xix-utils-timetool-incrementMonth-start.txt
tests/doctests/txt/xix-utils-timetool-setDayOfMonth-exceptions.txt
tests/doctests/txt/xix-utils-timetool-setDayOfWeek-monday.txt
tests/doctests/txt/xix-utils-timetool-setDayOfWeek-startsun-BUG1.txt
tests/doctests/txt/xix-utils-timetool-setDayOfWeek-startsun-monday.txt
tests/doctests/txt/xix-utils-timetool-setDayOfWeek-startsun.txt
tests/doctests/txt/xix-utils-upgrade.txt
tests/doctests/utils/__init__.py
tests/doctests/utils/__testcfg__.cfg
tests/doctests/utils/config.py
tests/doctests/utils/python.py
tests/doctests/utils/rules.py
tests/site-packages/README
xix_utils.egg-info/PKG-INFO
xix_utils.egg-info/SOURCES.txt
xix_utils.egg-info/dependency_links.txt
xix_utils.egg-info/entry_points.txt
xix_utils.egg-info/requires.txt
xix_utils.egg-info/top_level.txt
