Metadata-Version: 1.0
Name: xix-utils
Version: 0.2.4
Summary: Xix Utils is a drillbit library independent (mostly) of
Home-page: http://xix.python-hosting.com
Author: Drew Smathers
Author-email: drew dot smathers at gmail dot com
License: MIT License
Platform: UNKNOWN
Classifier: Development Status :: 4 - Beta
Classifier: License :: OSI Approved :: MIT License
Classifier: Operating System :: MacOS :: MacOS X
Classifier: Operating System :: Microsoft :: Windows
Classifier: Operating System :: POSIX
Classifier: Environment :: Console
Classifier: Programming Language :: Python
Classifier: Intended Audience :: Developers
Classifier: Topic :: Software Development :: Libraries :: Python Modules
Classifier: Topic :: Utilities
